cryptum/__init__.py
cryptum/cryptapp.py
cryptum/encryption.py
cryptum-0.0.3.dist-info/LICENSE
cryptum-0.0.3.dist-info/METADATA
cryptum-0.0.3.dist-info/WHEEL
cryptum-0.0.3.dist-info/entry_points.txt
cryptum-0.0.3.dist-info/top_level.txt
cryptum-0.0.3.dist-info/RECORD
