Metadata-Version: 2.1
Name: cryptum
Version: 0.0.3
Summary: A simple Python encryption library
Author-email: Your Name <your.email@example.com>
License: Apache License
Project-URL: Homepage, https://github.com/AUCR/cryptum
Project-URL: Bug Tracker, https://github.com/AUCR/cryptum/issues
Keywords: encryption,RSA,cryptography
Classifier: Programming Language :: Python :: 3
Classifier: License :: OSI Approved :: MIT License
Classifier: Operating System :: OS Independent
Requires-Python: >=3.7
License-File: LICENSE
Requires-Dist: cryptography
Requires-Dist: click
